examples/__init__.py
examples/markface/tweet_sentiment_analysis.py
examples/marklearn/car_prediction.py
examples/marklearn/malware_detection.py
examples/marklearn/malware_detection_dawn.py
examples/marklearn/utils.py
examples/marklearn/data/car_data.csv
examples/marklearn/data/malware_detection.csv
examples/marktorch/mnist_dawn.py
examples/marktorch/mnist_merrer.py
examples/marktorch/mnist_noise.py
examples/marktorch/mnist_patch.py
examples/marktorch/mnist_selected.py
examples/marktorch/utils.py
examples/marktorch/trigger_set/labels-cifar.txt
examples/marktorch/trigger_set/0/1.jpg
examples/marktorch/trigger_set/0/10.jpg
examples/marktorch/trigger_set/0/2.jpg
examples/marktorch/trigger_set/0/3.jpg
examples/marktorch/trigger_set/0/4.jpg
examples/marktorch/trigger_set/0/5.jpg
examples/marktorch/trigger_set/0/6.jpg
examples/marktorch/trigger_set/0/7.jpg
examples/marktorch/trigger_set/0/8.jpg
examples/marktorch/trigger_set/0/9.jpg
examples/marktorch/trigger_set/1/11.jpg
examples/marktorch/trigger_set/1/12.jpg
examples/marktorch/trigger_set/1/13.jpg
examples/marktorch/trigger_set/1/14.jpg
examples/marktorch/trigger_set/1/15.jpg
examples/marktorch/trigger_set/1/16.jpg
examples/marktorch/trigger_set/1/17.jpg
examples/marktorch/trigger_set/1/18.jpg
examples/marktorch/trigger_set/1/19.jpg
examples/marktorch/trigger_set/1/20.jpg
examples/marktorch/trigger_set/2/21.jpg
examples/marktorch/trigger_set/2/22.jpg
examples/marktorch/trigger_set/2/23.jpg
examples/marktorch/trigger_set/2/24.jpg
examples/marktorch/trigger_set/2/25.jpg
examples/marktorch/trigger_set/2/26.jpg
examples/marktorch/trigger_set/2/27.jpg
examples/marktorch/trigger_set/2/28.jpg
examples/marktorch/trigger_set/2/29.jpg
examples/marktorch/trigger_set/2/30.jpg
examples/marktorch/trigger_set/3/31.jpg
examples/marktorch/trigger_set/3/32.jpg
examples/marktorch/trigger_set/3/33.jpg
examples/marktorch/trigger_set/3/34.jpg
examples/marktorch/trigger_set/3/35.jpg
examples/marktorch/trigger_set/3/36.jpg
mlmodelwatermarking-0.0.1.dist-info/LICENSE
mlmodelwatermarking-0.0.1.dist-info/METADATA
mlmodelwatermarking-0.0.1.dist-info/WHEEL
mlmodelwatermarking-0.0.1.dist-info/top_level.txt
mlmodelwatermarking-0.0.1.dist-info/RECORD
