Metadata-Version: 2.1
Name: mlmodelwatermarking
Version: 0.0.1
Summary: ML Model Watermarking
Home-page: https://www.sap.com/
Author: SAP SE
License: UNKNOWN
Project-URL: Source, https://github.com/SAP/ml-model-watermarking
Keywords: watermarking SAP
Platform: UNKNOWN
Classifier: Programming Language :: Python :: 3
Classifier: Operating System :: OS Independent
Classifier: License :: OSI Approved :: Apache Software License
Classifier: Intended Audience :: Developers
Classifier: Development Status :: 3 - Alpha
Requires-Python: >3.5, <3.10
License-File: LICENSE
Requires-Dist: cryptography
Requires-Dist: numpy
Requires-Dist: sklearn
Requires-Dist: torch
Requires-Dist: transformers
Requires-Dist: datasets
Requires-Dist: torchvision
Requires-Dist: pyfiglet
Requires-Dist: tqdm
Requires-Dist: bitstring
